alphatrading/__init__.py
alphatrading/simulation/__init__.py
alphatrading/simulation/backtester/__init__.py
alphatrading/simulation/backtester/analysis.py
alphatrading/simulation/backtester/data.py
alphatrading/simulation/backtester/diagnostics.py
alphatrading/simulation/backtester/financialTools.py
alphatrading/simulation/backtester/order.py
alphatrading/simulation/backtester/portfolio.py
alphatrading/simulation/backtester/position.py
alphatrading/simulation/backtester/simulation.py
alphatrading/simulation/backtester/symbol.py
alphatrading/simulation/backtester/system.py
alphatrading/simulation/backtester/utils.py
alphatrading/simulation/backtester/writer.py
alphatrading/simulation/backtester/models/__init__.py
alphatrading/simulation/backtester/models/slippage.py
alphatrading/simulation/backtester/models/spread.py
alphatrading/simulation/quanTest/__init__.py
alphatrading/simulation/quanTest/analysis.py
alphatrading/simulation/quanTest/data.py
alphatrading/simulation/quanTest/diagnostics.py
alphatrading/simulation/quanTest/financialTools.py
alphatrading/simulation/quanTest/main.py
alphatrading/simulation/quanTest/order.py
alphatrading/simulation/quanTest/portfolio.py
alphatrading/simulation/quanTest/position.py
alphatrading/simulation/quanTest/simulation.py
alphatrading/simulation/quanTest/symbol.py
alphatrading/simulation/quanTest/system.py
alphatrading/simulation/quanTest/utils.py
alphatrading/simulation/quanTest/writer.py
alphatrading/simulation/quanTest/models/__init__.py
alphatrading/simulation/quanTest/models/slippage.py
alphatrading/simulation/quanTest/models/spread.py
alphatrading/system/__init__.py
alphatrading/system/database.py
alphatrading/system/db_methods/__init__.py
alphatrading/system/db_methods/method_sqlite3.py
alphatrading/trading/__init__.py
alphatrading/trading/quanTrade/__init__.py
alphatrading/trading/quanTrade/client.py
alphatrading/trading/quanTrade/client_IBKR.py
alphatrading/trading/quanTrade/client_MT4.py
q26_alphatrading-0.1.1.dist-info/LICENSE.md
q26_alphatrading-0.1.1.dist-info/METADATA
q26_alphatrading-0.1.1.dist-info/WHEEL
q26_alphatrading-0.1.1.dist-info/top_level.txt
q26_alphatrading-0.1.1.dist-info/RECORD
