Metadata-Version: 2.1
Name: q26-alphatrading
Version: 0.1.1
Summary: A python package for trading
Home-page: UNKNOWN
Author: Loann Brahimi
Author-email: loann.brahimi@outlook.fr
License: UNKNOWN
Platform: UNKNOWN
Classifier: Programming Language :: Python :: 3
Classifier: License :: OSI Approved :: MIT License
Classifier: Operating System :: OS Independent
Requires-Python: >=3.6
License-File: LICENSE.md
